{
    "name":"fileinput",
    "zpy":"fileinput",
    "functions":[
        {
            "name":"S_IFIFO",
            "zpy":"S_IFIFO"
        },
        {
            "name":"UF_APPEND",
            "zpy":"佛罗里达大学附加"
        },
        {
            "name":"S_IROTH",
            "zpy":"S_IROTH"
        },
        {
            "name":"S_ISWHT",
            "zpy":"S_ISWHT"
        },
        {
            "name":"S_IFLNK",
            "zpy":"S_IFLNK"
        },
        {
            "name":"FILE_ATTRIBUTE_SYSTEM",
            "zpy":"文件属性系统"
        },
        {
            "name":"S_IXOTH",
            "zpy":"S_IXOTH"
        },
        {
            "name":"FILE_ATTRIBUTE_NOT_CONTENT_INDEXED",
            "zpy":"文件属性没有内容索引"
        },
        {
            "name":"ST_MODE",
            "zpy":"圣模式"
        },
        {
            "name":"S_ISVTX",
            "zpy":"S_ISVTX"
        },
        {
            "name":"FILE_ATTRIBUTE_INTEGRITY_STREAM",
            "zpy":"文件属性完整性流"
        },
        {
            "name":"S_ISDOOR",
            "zpy":"S_ISDOOR"
        },
        {
            "name":"S_ISREG",
            "zpy":"S_ISREG"
        },
        {
            "name":"FILE_ATTRIBUTE_ARCHIVE",
            "zpy":"归档文件属性"
        },
        {
            "name":"FILE_ATTRIBUTE_READONLY",
            "zpy":"文件属性只读的"
        },
        {
            "name":"S_IFWHT",
            "zpy":"S_IFWHT"
        },
        {
            "name":"S_ISFIFO",
            "zpy":"S_ISFIFO"
        },
        {
            "name":"S_IEXEC",
            "zpy":"S_IEXEC"
        },
        {
            "name":"S_IMODE",
            "zpy":"将"
        },
        {
            "name":"S_IWUSR",
            "zpy":"S_IWUSR"
        },
        {
            "name":"S_IFREG",
            "zpy":"S_IFREG"
        },
        {
            "name":"ST_MTIME",
            "zpy":"圣MTIME"
        },
        {
            "name":"S_IFSOCK",
            "zpy":"S_IFSOCK"
        },
        {
            "name":"UF_IMMUTABLE",
            "zpy":"佛罗里达大学不可变的"
        },
        {
            "name":"FILE_ATTRIBUTE_DEVICE",
            "zpy":"文件属性装置"
        },
        {
            "name":"filemode",
            "zpy":"文件模式"
        },
        {
            "name":"S_IXUSR",
            "zpy":"S_IXUSR"
        },
        {
            "name":"UF_NODUMP",
            "zpy":"佛罗里达大学NODUMP"
        },
        {
            "name":"FILE_ATTRIBUTE_COMPRESSED",
            "zpy":"压缩文件属性"
        },
        {
            "name":"UF_OPAQUE",
            "zpy":"佛罗里达大学不透明"
        },
        {
            "name":"S_ENFMT",
            "zpy":"S_ENFMT"
        },
        {
            "name":"FILE_ATTRIBUTE_DIRECTORY",
            "zpy":"文件属性目录"
        },
        {
            "name":"SF_ARCHIVED",
            "zpy":"科幻存档"
        },
        {
            "name":"S_IFMT",
            "zpy":"S_IFMT"
        },
        {
            "name":"FILE_ATTRIBUTE_HIDDEN",
            "zpy":"文件属性隐藏"
        },
        {
            "name":"FILE_ATTRIBUTE_TEMPORARY",
            "zpy":"临时文件属性"
        },
        {
            "name":"UF_HIDDEN",
            "zpy":"佛罗里达大学隐藏起来"
        },
        {
            "name":"SF_SNAPSHOT",
            "zpy":"科幻快照"
        },
        {
            "name":"FILE_ATTRIBUTE_SPARSE_FILE",
            "zpy":"稀疏文件"
        },
        {
            "name":"ST_INO",
            "zpy":"圣伊诺"
        },
        {
            "name":"S_IWRITE",
            "zpy":"S_IWRITE"
        },
        {
            "name":"FILE_ATTRIBUTE_OFFLINE",
            "zpy":"离线文件属性"
        },
        {
            "name":"S_IREAD",
            "zpy":"S_IREAD"
        },
        {
            "name":"S_ISSOCK",
            "zpy":"S_ISSOCK"
        },
        {
            "name":"SF_NOUNLINK",
            "zpy":"科幻NOUNLINK"
        },
        {
            "name":"S_ISLNK",
            "zpy":"S_ISLNK"
        },
        {
            "name":"S_ISBLK",
            "zpy":"S_ISBLK"
        },
        {
            "name":"FILE_ATTRIBUTE_NO_SCRUB_DATA",
            "zpy":"文件属性没有擦洗数据"
        },
        {
            "name":"FILE_ATTRIBUTE_VIRTUAL",
            "zpy":"虚拟文件属性"
        },
        {
            "name":"S_IRGRP",
            "zpy":"S_IRGRP"
        },
        {
            "name":"S_IRUSR",
            "zpy":"S_IRUSR"
        },
        {
            "name":"S_ISPORT",
            "zpy":"S_ISPORT"
        },
        {
            "name":"S_IXGRP",
            "zpy":"S_IXGRP"
        },
        {
            "name":"S_IFDIR",
            "zpy":"S_IFDIR"
        },
        {
            "name":"IO_REPARSE_TAG_APPEXECLINK",
            "zpy":"IO重解析标签appexeclink"
        },
        {
            "name":"ST_UID",
            "zpy":"圣UID"
        },
        {
            "name":"ST_SIZE",
            "zpy":"圣的大小"
        },
        {
            "name":"UF_COMPRESSED",
            "zpy":"佛罗里达大学压缩"
        },
        {
            "name":"S_ISDIR",
            "zpy":"S_ISDIR"
        },
        {
            "name":"S_ISUID",
            "zpy":"S_ISUID"
        },
        {
            "name":"S_IFBLK",
            "zpy":"S_IFBLK"
        },
        {
            "name":"S_ISGID",
            "zpy":"S_ISGID"
        },
        {
            "name":"SF_IMMUTABLE",
            "zpy":"科幻小说不可变的"
        },
        {
            "name":"ST_ATIME",
            "zpy":"圣ATIME"
        },
        {
            "name":"FILE_ATTRIBUTE_ENCRYPTED",
            "zpy":"文件属性加密"
        },
        {
            "name":"SF_APPEND",
            "zpy":"科幻追加"
        },
        {
            "name":"UF_NOUNLINK",
            "zpy":"佛罗里达大学NOUNLINK"
        },
        {
            "name":"FILE_ATTRIBUTE_REPARSE_POINT",
            "zpy":"文件属性重解析点"
        },
        {
            "name":"ST_GID",
            "zpy":"圣GID"
        },
        {
            "name":"S_IFCHR",
            "zpy":"S_IFCHR"
        },
        {
            "name":"FILE_ATTRIBUTE_NORMAL",
            "zpy":"文件属性正常"
        },
        {
            "name":"S_IFDOOR",
            "zpy":"S_IFDOOR"
        },
        {
            "name":"ST_NLINK",
            "zpy":"圣NLINK"
        },
        {
            "name":"S_IWGRP",
            "zpy":"S_IWGRP"
        },
        {
            "name":"ST_CTIME",
            "zpy":"圣CTIME"
        },
        {
            "name":"S_IWOTH",
            "zpy":"S_IWOTH"
        },
        {
            "name":"S_IRWXG",
            "zpy":"S_IRWXG"
        },
        {
            "name":"IO_REPARSE_TAG_MOUNT_POINT",
            "zpy":"IO重新解析标签挂载点"
        },
        {
            "name":"S_ISCHR",
            "zpy":"S_ISCHR"
        },
        {
            "name":"IO_REPARSE_TAG_SYMLINK",
            "zpy":"IO重解析标记符号链接"
        },
        {
            "name":"S_IRWXU",
            "zpy":"S_IRWXU"
        },
        {
            "name":"S_IRWXO",
            "zpy":"S_IRWXO"
        },
        {
            "name":"S_IFPORT",
            "zpy":"S_IFPORT"
        },
        {
            "name":"ST_DEV",
            "zpy":"圣开"
        }
    ],
    "args":[
        {
            "name":"S_ISREG",
            "zpy":"S_ISREG"
        },
        {
            "name":"visitfile",
            "zpy":"访问文件"
        },
        {
            "name":"mode",
            "zpy":"模式"
        },
        {
            "name":"join",
            "zpy":"加入"
        },
        {
            "name":"listdir",
            "zpy":"列目录命令"
        },
        {
            "name":"path",
            "zpy":"路径"
        },
        {
            "name":"st_mode",
            "zpy":"圣模式"
        },
        {
            "name":"callback",
            "zpy":"收回"
        },
        {
            "name":"pathname",
            "zpy":"路径名"
        },
        {
            "name":"stat",
            "zpy":"静"
        },
        {
            "name":"argv",
            "zpy":"argv"
        },
        {
            "name":"walktree",
            "zpy":"行走的树"
        },
        {
            "name":"file",
            "zpy":"文件"
        },
        {
            "name":"S_ISDIR",
            "zpy":"S_ISDIR"
        }
    ]
}