{
    "name":"urllib.request",
    "zpy":"urllib.request",
    "functions":[
        {
            "name":"http_error_407",
            "zpy":"http错误407"
        },
        {
            "name":"FileHandler",
            "zpy":"文件处理程序"
        },
        {
            "name":"AbstractDigestAuthHandler",
            "zpy":"摘要DigestAuthHandler"
        },
        {
            "name":"selector",
            "zpy":"选择者"
        },
        {
            "name":"setMaxConns",
            "zpy":"设置MaxConns"
        },
        {
            "name":"UnknownHandler",
            "zpy":"未知的处理程序"
        },
        {
            "name":"code",
            "zpy":"代码"
        },
        {
            "name":"add_parent",
            "zpy":"加上父母"
        },
        {
            "name":"BaseHandler",
            "zpy":"基础处理程序"
        },
        {
            "name":"update_authenticated",
            "zpy":"更新验证"
        },
        {
            "name":"pathname2url",
            "zpy":"路径名2url"
        },
        {
            "name":"CacheFTPHandler",
            "zpy":"缓存FTP处理程序"
        },
        {
            "name":"type",
            "zpy":"类型"
        },
        {
            "name":"get_full_url",
            "zpy":"得到完整的url"
        },
        {
            "name":"FTPHandler",
            "zpy":"FTP处理程序"
        },
        {
            "name":"add_unredirected_header",
            "zpy":"添加unredirected头"
        },
        {
            "name":"cookiejar",
            "zpy":"饼干罐"
        },
        {
            "name":"origin_req_host",
            "zpy":"起源要求的主机"
        },
        {
            "name":"HTTPPasswordMgrWithDefaultRealm",
            "zpy":"HTTP密码MgrWithDefaultRealm"
        },
        {
            "name":"addinfourl",
            "zpy":"加上4个l"
        },
        {
            "name":"https_response",
            "zpy":"https的回应"
        },
        {
            "name":"HTTPRedirectHandler",
            "zpy":"HTTP重定向处理程序"
        },
        {
            "name":"ProxyHandler",
            "zpy":"代理处理程序"
        },
        {
            "name":"urlcleanup",
            "zpy":"url清理"
        },
        {
            "name":"open_unknown",
            "zpy":"打开未知"
        },
        {
            "name":"http_response",
            "zpy":"http响应"
        },
        {
            "name":"method",
            "zpy":"方法"
        },
        {
            "name":"full_url",
            "zpy":"完整的url"
        },
        {
            "name":"default_open",
            "zpy":"默认打开"
        },
        {
            "name":"parent",
            "zpy":"父母"
        },
        {
            "name":"install_opener",
            "zpy":"安装刀"
        },
        {
            "name":"BaseHandler.http_error_<nnn>(req, fp, code, msg, hdrs)",
            "zpy":"BaseHandlerHTTP错误NNN"
        },
        {
            "name":"get_header",
            "zpy":"头"
        },
        {
            "name":"close",
            "zpy":"结束"
        },
        {
            "name":"ProxyBasicAuthHandler",
            "zpy":"代理基本Au处理程序"
        },
        {
            "name":"AbstractBasicAuthHandler",
            "zpy":"摘要基本Au处理器"
        },
        {
            "name":"host",
            "zpy":"主人"
        },
        {
            "name":"status",
            "zpy":"状态"
        },
        {
            "name":"HTTPCookieProcessor",
            "zpy":"HTTPCookie处理器"
        },
        {
            "name":"http_error_301",
            "zpy":"http错误301"
        },
        {
            "name":"BaseHandler.<protocol>_request(req)",
            "zpy":"BaseHandler协议请求"
        },
        {
            "name":"https_open",
            "zpy":"https开放"
        },
        {
            "name":"FancyURLopener",
            "zpy":"花哨的URL的开瓶器"
        },
        {
            "name":"DataHandler",
            "zpy":"数据处理程序"
        },
        {
            "name":"unverifiable",
            "zpy":"不能证实的"
        },
        {
            "name":"ProxyHandler.<protocol>_open(request)",
            "zpy":"ProxyHandler.<protocol>_open(request)"
        },
        {
            "name":"is_authenticated",
            "zpy":"是经过验证的"
        },
        {
            "name":"error",
            "zpy":"错误"
        },
        {
            "name":"retrieve",
            "zpy":"取回"
        },
        {
            "name":"OpenerDirector",
            "zpy":"首场比赛"
        },
        {
            "name":"data_open",
            "zpy":"数据开放"
        },
        {
            "name":"http_error_default",
            "zpy":"http错误违约"
        },
        {
            "name":"BaseHandler.<protocol>_response(req, response)",
            "zpy":"BaseHandler协议响应"
        },
        {
            "name":"find_user_password",
            "zpy":"找到用户密码"
        },
        {
            "name":"HTTPErrorProcessor",
            "zpy":"HTTP错误处理器"
        },
        {
            "name":"HTTPSHandler",
            "zpy":"http处理程序"
        },
        {
            "name":"remove_header",
            "zpy":"删除标题"
        },
        {
            "name":"http_error_401",
            "zpy":"http错误401"
        },
        {
            "name":"getstatus",
            "zpy":"状态"
        },
        {
            "name":"HTTPPasswordMgr",
            "zpy":"HTTP密码Mgr"
        },
        {
            "name":"set_proxy",
            "zpy":"设置代理"
        },
        {
            "name":"url2pathname",
            "zpy":"Url2路径名"
        },
        {
            "name":"prompt_user_passwd",
            "zpy":"提示用户密码"
        },
        {
            "name":"HTTPDefaultErrorHandler",
            "zpy":"HTTP默认错误处理程序"
        },
        {
            "name":"Request",
            "zpy":"请求"
        },
        {
            "name":"ftp_open",
            "zpy":"ftp开放"
        },
        {
            "name":"redirect_request",
            "zpy":"重定向请求"
        },
        {
            "name":"getproxies",
            "zpy":"代理"
        },
        {
            "name":"add_handler",
            "zpy":"添加处理程序"
        },
        {
            "name":"setTimeout",
            "zpy":"设置超时"
        },
        {
            "name":"HTTPDigestAuthHandler",
            "zpy":"HTTPDigestAuthHandler"
        },
        {
            "name":"http_error_302",
            "zpy":"http错误302"
        },
        {
            "name":"build_opener",
            "zpy":"构建器"
        },
        {
            "name":"HTTPHandler",
            "zpy":"HTTP处理程序"
        },
        {
            "name":"HTTPPasswordMgrWithPriorAuth",
            "zpy":"HTTP密码MgrWithPriorAu"
        },
        {
            "name":"header_items",
            "zpy":"头项目"
        },
        {
            "name":"get_method",
            "zpy":"get方法"
        },
        {
            "name":"ProxyDigestAuthHandler",
            "zpy":"代理DigestAu处理程序"
        },
        {
            "name":"http_error_307",
            "zpy":"http错误307"
        },
        {
            "name":"unknown_open",
            "zpy":"未知的开放"
        },
        {
            "name":"http_error_303",
            "zpy":"http错误303"
        },
        {
            "name":"urlretrieve",
            "zpy":"url检索"
        },
        {
            "name":"has_header",
            "zpy":"头"
        },
        {
            "name":"BaseHandler.<protocol>_open(req)",
            "zpy":"BaseHandler协议open"
        },
        {
            "name":"file_open",
            "zpy":"文件打开"
        },
        {
            "name":"http_error_auth_reqed",
            "zpy":"HTTP认证错误"
        },
        {
            "name":"info",
            "zpy":"信息"
        },
        {
            "name":"add_header",
            "zpy":"添加标题"
        },
        {
            "name":"headers",
            "zpy":"标题"
        },
        {
            "name":"HTTPBasicAuthHandler",
            "zpy":"HTTP基本的Au处理程序"
        },
        {
            "name":"add_password",
            "zpy":"添加密码"
        },
        {
            "name":"version",
            "zpy":"一种描述"
        },
        {
            "name":"geturl",
            "zpy":"网址"
        },
        {
            "name":"URLopener",
            "zpy":"URL刀"
        },
        {
            "name":"urlopen",
            "zpy":"url打开"
        },
        {
            "name":"http_open",
            "zpy":"http开放"
        },
        {
            "name":"open",
            "zpy":"开"
        },
        {
            "name":"data",
            "zpy":"数据"
        }
    ],
    "args":[
        {
            "name":"decode",
            "zpy":"解码"
        },
        {
            "name":"proxy_handler",
            "zpy":"代理处理程序"
        },
        {
            "name":"x509",
            "zpy":"x509"
        },
        {
            "name":"proto",
            "zpy":"原型"
        },
        {
            "name":"code",
            "zpy":"代码"
        },
        {
            "name":"authreq",
            "zpy":"在这里"
        },
        {
            "name":"proxies",
            "zpy":"代表权巡游费"
        },
        {
            "name":"check_hostname",
            "zpy":"检查主机名"
        },
        {
            "name":"type",
            "zpy":"类型"
        },
        {
            "name":"cookiejar",
            "zpy":"饼干罐"
        },
        {
            "name":"realm",
            "zpy":"王国"
        },
        {
            "name":"origin_req_host",
            "zpy":"起源要求的主机"
        },
        {
            "name":"stdin",
            "zpy":"标准输入"
        },
        {
            "name":"authuri",
            "zpy":"非盟thuri"
        },
        {
            "name":"ProxyHandler",
            "zpy":"代理处理程序"
        },
        {
            "name":"filename",
            "zpy":"文件名"
        },
        {
            "name":"request",
            "zpy":"请求"
        },
        {
            "name":"fullurl",
            "zpy":"fullurl"
        },
        {
            "name":"urllib",
            "zpy":"url自由"
        },
        {
            "name":"method",
            "zpy":"方法"
        },
        {
            "name":"director",
            "zpy":"主管"
        },
        {
            "name":"reporthook",
            "zpy":"报告钩"
        },
        {
            "name":"install_opener",
            "zpy":"安装刀"
        },
        {
            "name":"hdrs",
            "zpy":"Hamiltondepressionratingscale哈密尔顿抑郁症等级量表"
        },
        {
            "name":"default",
            "zpy":"违约"
        },
        {
            "name":"close",
            "zpy":"结束"
        },
        {
            "name":"ProxyBasicAuthHandler",
            "zpy":"代理基本Au处理程序"
        },
        {
            "name":"host",
            "zpy":"主人"
        },
        {
            "name":"self",
            "zpy":"自己"
        },
        {
            "name":"context",
            "zpy":"上下文"
        },
        {
            "name":"status",
            "zpy":"状态"
        },
        {
            "name":"user",
            "zpy":"使用者"
        },
        {
            "name":"response",
            "zpy":"反应"
        },
        {
            "name":"encode",
            "zpy":"编码"
        },
        {
            "name":"FancyURLopener",
            "zpy":"花哨的URL的开瓶器"
        },
        {
            "name":"unverifiable",
            "zpy":"不能证实的"
        },
        {
            "name":"is_authenticated",
            "zpy":"是经过验证的"
        },
        {
            "name":"proxy_auth_handler",
            "zpy":"代理身份验证处理程序"
        },
        {
            "name":"DATA",
            "zpy":"资料"
        },
        {
            "name":"reason",
            "zpy":"理由"
        },
        {
            "name":"header_name",
            "zpy":"标题名称"
        },
        {
            "name":"args",
            "zpy":"参数"
        },
        {
            "name":"parse",
            "zpy":"从语法上分析"
        },
        {
            "name":"local_filename",
            "zpy":"本地文件名"
        },
        {
            "name":"debuglevel",
            "zpy":"调试水平"
        },
        {
            "name":"path",
            "zpy":"路径"
        },
        {
            "name":"opener",
            "zpy":"开启器"
        },
        {
            "name":"Request",
            "zpy":"请求"
        },
        {
            "name":"read",
            "zpy":"读"
        },
        {
            "name":"urlencode",
            "zpy":"urlencode"
        },
        {
            "name":"auth_handler",
            "zpy":"身份验证处理程序"
        },
        {
            "name":"addheaders",
            "zpy":"添加标题"
        },
        {
            "name":"build_opener",
            "zpy":"构建器"
        },
        {
            "name":"params",
            "zpy":"参数"
        },
        {
            "name":"newurl",
            "zpy":"新网址"
        },
        {
            "name":"urlretrieve",
            "zpy":"url检索"
        },
        {
            "name":"passwd",
            "zpy":"口令"
        },
        {
            "name":"add_header",
            "zpy":"添加标题"
        },
        {
            "name":"headers",
            "zpy":"标题"
        },
        {
            "name":"password_mgr",
            "zpy":"密码下"
        },
        {
            "name":"handler",
            "zpy":"处理者"
        },
        {
            "name":"HTTPBasicAuthHandler",
            "zpy":"HTTP基本的Au处理程序"
        },
        {
            "name":"add_password",
            "zpy":"添加密码"
        },
        {
            "name":"html",
            "zpy":"超文本标记语言"
        },
        {
            "name":"urlopen",
            "zpy":"url打开"
        },
        {
            "name":"header",
            "zpy":"收割台"
        },
        {
            "name":"open",
            "zpy":"开"
        },
        {
            "name":"data",
            "zpy":"数据"
        }
    ]
}