{
    "name":"webbrowser",
    "zpy":"webbrowser",
    "functions":[
        {
            "name":"register",
            "zpy":"寄存器"
        },
        {
            "name":"open_new",
            "zpy":"打开新的"
        },
        {
            "name":"open_new_tab",
            "zpy":"打开新标签页"
        },
        {
            "name":"open",
            "zpy":"开"
        },
        {
            "name":"Error",
            "zpy":"错误"
        }
    ],
    "args":[
        {
            "name":"python",
            "zpy":"大蟒"
        },
        {
            "name":"webbrowser",
            "zpy":"web浏览器"
        },
        {
            "name":"using",
            "zpy":"使用"
        },
        {
            "name":"preferred",
            "zpy":"首选的"
        },
        {
            "name":"instance",
            "zpy":"建议"
        },
        {
            "name":"name",
            "zpy":"名字"
        },
        {
            "name":"open_new",
            "zpy":"打开新的"
        },
        {
            "name":"open_new_tab",
            "zpy":"打开新标签页"
        },
        {
            "name":"autoraise",
            "zpy":"汽车增加"
        },
        {
            "name":"constructor",
            "zpy":"建造者"
        }
    ]
}